{
    "os": "Linux-5.3.18-57-default-x86_64-with-glibc2.17",
    "python": "3.8.13",
    "heartbeatAt": "2022-08-30T02:45:01.273427",
    "startedAt": "2022-08-30T02:44:59.561644",
    "docker": null,
    "gpu": "NVIDIA A100-SXM4-40GB",
    "gpu_count": 4,
    "cpu_count": 64,
    "cuda": null,
    "args": [
        "+mpi.local_size=4",
        "+wandb=True",
        "--config-name",
        "test_128x4x1"
    ],
    "state": "running",
    "program": "./main.py",
    "codePath": "cosmoflow/pytorch/main.py",
    "git": {
        "remote": "https://zhenghh04:@gitlab.com/nvidia-mlperf-hpc/optimized-hpc.git",
        "commit": "555364e31f2f9a4ca0f2684492161d4cb4157de3"
    },
    "email": "huihuo.zheng@anl.gov",
    "root": "/lus/grand/projects/datascience/hzheng/mlperf-2022/optimized-hpc",
    "host": "x3015c0s1b0n0",
    "username": "hzheng",
    "executable": "/var/run/palsd/5f0f7c3c-5a82-4ba8-9bf7-5270f78ea352/files/python"
}
